abdel/__init__.py
abdel/abd.py
abdel-0.0.2.dist-info/METADATA
abdel-0.0.2.dist-info/WHEEL
abdel-0.0.2.dist-info/top_level.txt
abdel-0.0.2.dist-info/RECORD
