Metadata-Version: 2.1
Name: abdel
Version: 0.0.2
Summary: Useful tools for further development of AI projects
Home-page: https://github.com/AbdelrahmanAbounida/wartsila-ai
Author: Abdelrahman Abounida
Author-email: abdelrahman.abounida@wartsila.com
License: UNKNOWN
Platform: UNKNOWN
Classifier: Programming Language :: Python :: 3
Classifier: License :: OSI Approved :: MIT License
Classifier: Operating System :: OS Independent
